plextraktsync/__init__.py
plextraktsync/__main__.py
plextraktsync/cli.py
plextraktsync/config.default.yml
plextraktsync/path.py
plextraktsync/pytrakt_extensions.py
plextraktsync/style.py
plextraktsync/commands/bug_report.py
plextraktsync/commands/cache.py
plextraktsync/commands/clear_collections.py
plextraktsync/commands/compare_libraries.py
plextraktsync/commands/config.py
plextraktsync/commands/download.py
plextraktsync/commands/imdb_import.py
plextraktsync/commands/info.py
plextraktsync/commands/inspect.py
plextraktsync/commands/login.py
plextraktsync/commands/plex_login.py
plextraktsync/commands/self_update.py
plextraktsync/commands/sync.py
plextraktsync/commands/trakt_login.py
plextraktsync/commands/unmatched.py
plextraktsync/commands/watch.py
plextraktsync/commands/watched_shows.py
plextraktsync/config/Config.py
plextraktsync/config/ConfigLoader.py
plextraktsync/config/ConfigMergeMixin.py
plextraktsync/config/HttpCacheConfig.py
plextraktsync/config/PlexServerConfig.py
plextraktsync/config/RunConfig.py
plextraktsync/config/ServerConfigFactory.py
plextraktsync/config/SyncConfig.py
plextraktsync/config/__init__.py
plextraktsync/decorators/account_limit.py
plextraktsync/decorators/coro.py
plextraktsync/decorators/flatten.py
plextraktsync/decorators/measure_time.py
plextraktsync/decorators/nocache.py
plextraktsync/decorators/rate_limit.py
plextraktsync/decorators/retry.py
plextraktsync/decorators/time_limit.py
plextraktsync/factory/Factory.py
plextraktsync/factory/__init__.py
plextraktsync/logger/filter.py
plextraktsync/logger/init.py
plextraktsync/media/Media.py
plextraktsync/media/MediaFactory.py
plextraktsync/mixin/ChangeNotifier.py
plextraktsync/mixin/SetWindowTitle.py
plextraktsync/plan/WalkConfig.py
plextraktsync/plan/WalkPlan.py
plextraktsync/plan/WalkPlanner.py
plextraktsync/plan/Walker.py
plextraktsync/plex/PlexApi.py
plextraktsync/plex/PlexAudioCodec.py
plextraktsync/plex/PlexId.py
plextraktsync/plex/PlexIdFactory.py
plextraktsync/plex/PlexLibraryItem.py
plextraktsync-0.34.19.dist-info/licenses/LICENSE
plextraktsync-0.34.19.dist-info/METADATA
plextraktsync-0.34.19.dist-info/WHEEL
plextraktsync-0.34.19.dist-info/entry_points.txt
plextraktsync-0.34.19.dist-info/top_level.txt
plextraktsync-0.34.19.dist-info/RECORD
