Metadata-Version: 2.4
Name: PlexTraktSync
Version: 0.34.19
Summary: Plex-Trakt-Sync is a two-way-sync between trakt.tv and Plex Media Server
License: MIT License
Project-URL: Homepage, https://github.com/Taxel/PlexTraktSync
Project-URL: Repository, https://github.com/Taxel/PlexTraktSync.git
Project-URL: Issues, https://github.com/Taxel/PlexTraktSync/issues
Classifier: Development Status :: 5 - Production/Stable
Classifier: Environment :: Console
Classifier: Operating System :: OS Independent
Classifier: License :: OSI Approved :: MIT License
Classifier: Programming Language :: Python :: 3
Classifier: Programming Language :: Python :: 3.9
Classifier: Programming Language :: Python :: 3.10
Classifier: Programming Language :: Python :: 3.11
Classifier: Programming Language :: Python :: 3.12
Requires-Python: >=3.9
License-File: LICENSE
Requires-Dist: apluggy==1.1.1; python_version >= "3.9"
Requires-Dist: attrs==25.4.0; python_version >= "3.9"
Requires-Dist: cattrs==25.3.0; python_version >= "3.9"
Requires-Dist: certifi==2025.10.5; python_version >= "3.7"
Requires-Dist: charset-normalizer==3.4.4; python_version >= "3.7"
Requires-Dist: click==8.1.8; python_version >= "3.7"
Requires-Dist: decorator==5.2.1; python_version >= "3.8"
Requires-Dist: deprecated==1.2.18; python_version >= "2.7" and python_version not in "3.0, 3.1, 3.2, 3.3"
Requires-Dist: exceptiongroup==1.3.0; python_version >= "3.7"
Requires-Dist: humanize==4.13.0; python_version >= "3.9"
Requires-Dist: idna==3.11; python_version >= "3.8"
Requires-Dist: inquirerpy==0.3.4
Requires-Dist: markdown-it-py==3.0.0; python_version >= "3.8"
Requires-Dist: mdurl==0.1.2; python_version >= "3.7"
Requires-Dist: oauthlib==3.3.1; python_version >= "3.8"
Requires-Dist: pfzy==0.3.4
Requires-Dist: platformdirs==4.5.0; python_version >= "3.10"
Requires-Dist: plexapi==4.17.1; python_version >= "3.9"
Requires-Dist: pluggy==1.6.0; python_version >= "3.9"
Requires-Dist: prompt-toolkit==3.0.52; python_version >= "3.8"
Requires-Dist: pygments==2.19.2; python_version >= "3.8"
Requires-Dist: python-dotenv==1.2.1; python_version >= "3.9"
Requires-Dist: python-git-info==0.8.3
Requires-Dist: pytimeparse==1.1.8
Requires-Dist: pytrakt==4.2.2
Requires-Dist: pyyaml==6.0.3; python_version >= "3.8"
Requires-Dist: requests==2.32.5; python_version >= "3.9"
Requires-Dist: requests-cache==1.2.1
Requires-Dist: requests-oauthlib==2.0.0; python_version >= "3.4"
Requires-Dist: rich==14.2.0; python_full_version >= "3.8.0"
Requires-Dist: six==1.17.0; python_version >= "2.7" and python_version not in "3.0, 3.1, 3.2, 3.3"
Requires-Dist: tqdm==4.67.1; python_version >= "3.7"
Requires-Dist: types-decorator==5.2.0.20251101; python_version >= "3.9"
Requires-Dist: typing-extensions==4.15.0; python_version >= "3.9"
Requires-Dist: url-normalize==2.2.1; python_version >= "3.8"
Requires-Dist: urllib3==2.5.0; python_version >= "3.9"
Requires-Dist: wcwidth==0.2.14; python_version >= "3.6"
Requires-Dist: websocket-client==1.9.0; python_version >= "3.9"
Requires-Dist: wrapt==1.17.3; python_version >= "3.8"
Dynamic: license-file
Dynamic: requires-dist
